<annotation>
	<folder>goodsid</folder>
	<filename>frames_00876.jpg</filename>
	<source>
		<database>The goodsid Database</database>
		<annotation>VC goodsid</annotation>
		<image>Unknow</image>
		<flickrid>Unknow</flickrid>
	</source>
	<owner>
		<flickrid>Unknow</flickrid>
		<name>Unknow</name>
	</owner>
	<size>
		<width>1080</width>
		<height>1920</height>
		<depth>3</depth>
	</size>
	<segmented>0</segmented>
	<object>
		<name>零食</name>
		<pose>Left</pose>
		<truncated>0</truncated>
		<difficult>0</difficult>
		<bndbox>
			<xmin>0</xmin>
			<ymin>336</ymin>
			<xmax>82</xmax>
			<ymax>609</ymax>
		</bndbox>
	</object>
	<object>
		<name>零食</name>
		<pose>Left</pose>
		<truncated>0</truncated>
		<difficult>0</difficult>
		<bndbox>
			<xmin>76</xmin>
			<ymin>345</ymin>
			<xmax>249</xmax>
			<ymax>607</ymax>
		</bndbox>
	</object>
	<object>
		<name>零食</name>
		<pose>Left</pose>
		<truncated>0</truncated>
		<difficult>0</difficult>
		<bndbox>
			<xmin>247</xmin>
			<ymin>297</ymin>
			<xmax>434</xmax>
			<ymax>513</ymax>
		</bndbox>
	</object>
	<object>
		<name>零食</name>
		<pose>Left</pose>
		<truncated>0</truncated>
		<difficult>0</difficult>
		<bndbox>
			<xmin>519</xmin>
			<ymin>306</ymin>
			<xmax>635</xmax>
			<ymax>490</ymax>
		</bndbox>
	</object>
	<object>
		<name>零食</name>
		<pose>Left</pose>
		<truncated>0</truncated>
		<difficult>0</difficult>
		<bndbox>
			<xmin>666</xmin>
			<ymin>359</ymin>
			<xmax>886</xmax>
			<ymax>613</ymax>
		</bndbox>
	</object>
	<object>
		<name>零食</name>
		<pose>Left</pose>
		<truncated>0</truncated>
		<difficult>0</difficult>
		<bndbox>
			<xmin>899</xmin>
			<ymin>288</ymin>
			<xmax>1080</xmax>
			<ymax>554</ymax>
		</bndbox>
	</object>
	<object>
		<name>零食</name>
		<pose>Left</pose>
		<truncated>0</truncated>
		<difficult>0</difficult>
		<bndbox>
			<xmin>0</xmin>
			<ymin>676</ymin>
			<xmax>123</xmax>
			<ymax>895</ymax>
		</bndbox>
	</object>
	<object>
		<name>零食</name>
		<pose>Left</pose>
		<truncated>0</truncated>
		<difficult>0</difficult>
		<bndbox>
			<xmin>133</xmin>
			<ymin>669</ymin>
			<xmax>269</xmax>
			<ymax>890</ymax>
		</bndbox>
	</object>
	<object>
		<name>零食</name>
		<pose>Left</pose>
		<truncated>0</truncated>
		<difficult>0</difficult>
		<bndbox>
			<xmin>266</xmin>
			<ymin>733</ymin>
			<xmax>450</xmax>
			<ymax>975</ymax>
		</bndbox>
	</object>
	<object>
		<name>零食</name>
		<pose>Left</pose>
		<truncated>0</truncated>
		<difficult>0</difficult>
		<bndbox>
			<xmin>439</xmin>
			<ymin>669</ymin>
			<xmax>617</xmax>
			<ymax>922</ymax>
		</bndbox>
	</object>
	<object>
		<name>零食</name>
		<pose>Left</pose>
		<truncated>0</truncated>
		<difficult>0</difficult>
		<bndbox>
			<xmin>652</xmin>
			<ymin>642</ymin>
			<xmax>838</xmax>
			<ymax>908</ymax>
		</bndbox>
	</object>
	<object>
		<name>零食</name>
		<pose>Left</pose>
		<truncated>0</truncated>
		<difficult>0</difficult>
		<bndbox>
			<xmin>878</xmin>
			<ymin>688</ymin>
			<xmax>1044</xmax>
			<ymax>924</ymax>
		</bndbox>
	</object>
	<object>
		<name>零食</name>
		<pose>Left</pose>
		<truncated>0</truncated>
		<difficult>0</difficult>
		<bndbox>
			<xmin>0</xmin>
			<ymin>996</ymin>
			<xmax>137</xmax>
			<ymax>1279</ymax>
		</bndbox>
	</object>
	<object>
		<name>零食</name>
		<pose>Left</pose>
		<truncated>0</truncated>
		<difficult>0</difficult>
		<bndbox>
			<xmin>145</xmin>
			<ymin>1020</ymin>
			<xmax>306</xmax>
			<ymax>1304</ymax>
		</bndbox>
	</object>
	<object>
		<name>零食</name>
		<pose>Left</pose>
		<truncated>0</truncated>
		<difficult>0</difficult>
		<bndbox>
			<xmin>364</xmin>
			<ymin>989</ymin>
			<xmax>514</xmax>
			<ymax>1226</ymax>
		</bndbox>
	</object>
	<object>
		<name>零食</name>
		<pose>Left</pose>
		<truncated>0</truncated>
		<difficult>0</difficult>
		<bndbox>
			<xmin>508</xmin>
			<ymin>971</ymin>
			<xmax>637</xmax>
			<ymax>1208</ymax>
		</bndbox>
	</object>
	<object>
		<name>零食</name>
		<pose>Left</pose>
		<truncated>0</truncated>
		<difficult>0</difficult>
		<bndbox>
			<xmin>663</xmin>
			<ymin>976</ymin>
			<xmax>847</xmax>
			<ymax>1226</ymax>
		</bndbox>
	</object>
	<object>
		<name>零食</name>
		<pose>Left</pose>
		<truncated>0</truncated>
		<difficult>0</difficult>
		<bndbox>
			<xmin>830</xmin>
			<ymin>939</ymin>
			<xmax>966</xmax>
			<ymax>1167</ymax>
		</bndbox>
	</object>
	<object>
		<name>零食</name>
		<pose>Left</pose>
		<truncated>0</truncated>
		<difficult>0</difficult>
		<bndbox>
			<xmin>81</xmin>
			<ymin>1314</ymin>
			<xmax>246</xmax>
			<ymax>1585</ymax>
		</bndbox>
	</object>
	<object>
		<name>零食</name>
		<pose>Left</pose>
		<truncated>0</truncated>
		<difficult>0</difficult>
		<bndbox>
			<xmin>227</xmin>
			<ymin>1323</ymin>
			<xmax>429</xmax>
			<ymax>1578</ymax>
		</bndbox>
	</object>
	<object>
		<name>零食</name>
		<pose>Left</pose>
		<truncated>0</truncated>
		<difficult>0</difficult>
		<bndbox>
			<xmin>410</xmin>
			<ymin>1275</ymin>
			<xmax>548</xmax>
			<ymax>1484</ymax>
		</bndbox>
	</object>
	<object>
		<name>零食</name>
		<pose>Left</pose>
		<truncated>0</truncated>
		<difficult>0</difficult>
		<bndbox>
			<xmin>529</xmin>
			<ymin>1280</ymin>
			<xmax>665</xmax>
			<ymax>1482</ymax>
		</bndbox>
	</object>
	<object>
		<name>零食</name>
		<pose>Left</pose>
		<truncated>0</truncated>
		<difficult>0</difficult>
		<bndbox>
			<xmin>677</xmin>
			<ymin>1277</ymin>
			<xmax>859</xmax>
			<ymax>1514</ymax>
		</bndbox>
	</object>
	<object>
		<name>零食</name>
		<pose>Left</pose>
		<truncated>0</truncated>
		<difficult>0</difficult>
		<bndbox>
			<xmin>876</xmin>
			<ymin>1243</ymin>
			<xmax>1035</xmax>
			<ymax>1473</ymax>
		</bndbox>
	</object>
	<object>
		<name>零食</name>
		<pose>Left</pose>
		<truncated>0</truncated>
		<difficult>0</difficult>
		<bndbox>
			<xmin>0</xmin>
			<ymin>1589</ymin>
			<xmax>107</xmax>
			<ymax>1800</ymax>
		</bndbox>
	</object>
	<object>
		<name>零食</name>
		<pose>Left</pose>
		<truncated>0</truncated>
		<difficult>0</difficult>
		<bndbox>
			<xmin>106</xmin>
			<ymin>1582</ymin>
			<xmax>278</xmax>
			<ymax>1784</ymax>
		</bndbox>
	</object>
	<object>
		<name>零食</name>
		<pose>Left</pose>
		<truncated>0</truncated>
		<difficult>0</difficult>
		<bndbox>
			<xmin>303</xmin>
			<ymin>1657</ymin>
			<xmax>525</xmax>
			<ymax>1836</ymax>
		</bndbox>
	</object>
	<object>
		<name>零食</name>
		<pose>Left</pose>
		<truncated>0</truncated>
		<difficult>0</difficult>
		<bndbox>
			<xmin>481</xmin>
			<ymin>1511</ymin>
			<xmax>633</xmax>
			<ymax>1731</ymax>
		</bndbox>
	</object>
	<object>
		<name>零食</name>
		<pose>Left</pose>
		<truncated>0</truncated>
		<difficult>0</difficult>
		<bndbox>
			<xmin>668</xmin>
			<ymin>1584</ymin>
			<xmax>838</xmax>
			<ymax>1829</ymax>
		</bndbox>
	</object>
	<object>
		<name>零食</name>
		<pose>Left</pose>
		<truncated>0</truncated>
		<difficult>0</difficult>
		<bndbox>
			<xmin>869</xmin>
			<ymin>1467</ymin>
			<xmax>1053</xmax>
			<ymax>1706</ymax>
		</bndbox>
	</object>
</annotation>