<annotation>
	<folder>goodsid</folder>
	<filename>frames_00642.jpg</filename>
	<source>
		<database>The goodsid Database</database>
		<annotation>VC goodsid</annotation>
		<image>Unknow</image>
		<flickrid>Unknow</flickrid>
	</source>
	<owner>
		<flickrid>Unknow</flickrid>
		<name>Unknow</name>
	</owner>
	<size>
		<width>1080</width>
		<height>1920</height>
		<depth>3</depth>
	</size>
	<segmented>0</segmented>
	<object>
		<name>零食</name>
		<pose>Left</pose>
		<truncated>0</truncated>
		<difficult>0</difficult>
		<bndbox>
			<xmin>0</xmin>
			<ymin>294</ymin>
			<xmax>43</xmax>
			<ymax>446</ymax>
		</bndbox>
	</object>
	<object>
		<name>零食</name>
		<pose>Left</pose>
		<truncated>0</truncated>
		<difficult>0</difficult>
		<bndbox>
			<xmin>0</xmin>
			<ymin>442</ymin>
			<xmax>49</xmax>
			<ymax>577</ymax>
		</bndbox>
	</object>
	<object>
		<name>零食</name>
		<pose>Left</pose>
		<truncated>0</truncated>
		<difficult>0</difficult>
		<bndbox>
			<xmin>0</xmin>
			<ymin>630</ymin>
			<xmax>49</xmax>
			<ymax>759</ymax>
		</bndbox>
	</object>
	<object>
		<name>零食</name>
		<pose>Left</pose>
		<truncated>0</truncated>
		<difficult>0</difficult>
		<bndbox>
			<xmin>0</xmin>
			<ymin>750</ymin>
			<xmax>52</xmax>
			<ymax>879</ymax>
		</bndbox>
	</object>
	<object>
		<name>零食</name>
		<pose>Left</pose>
		<truncated>0</truncated>
		<difficult>0</difficult>
		<bndbox>
			<xmin>0</xmin>
			<ymin>943</ymin>
			<xmax>63</xmax>
			<ymax>1170</ymax>
		</bndbox>
	</object>
	<object>
		<name>零食</name>
		<pose>Left</pose>
		<truncated>0</truncated>
		<difficult>0</difficult>
		<bndbox>
			<xmin>0</xmin>
			<ymin>1183</ymin>
			<xmax>76</xmax>
			<ymax>1435</ymax>
		</bndbox>
	</object>
	<object>
		<name>泡面</name>
		<pose>Left</pose>
		<truncated>0</truncated>
		<difficult>0</difficult>
		<bndbox>
			<xmin>0</xmin>
			<ymin>1437</ymin>
			<xmax>89</xmax>
			<ymax>1655</ymax>
		</bndbox>
	</object>
	<object>
		<name>泡面</name>
		<pose>Left</pose>
		<truncated>0</truncated>
		<difficult>0</difficult>
		<bndbox>
			<xmin>142</xmin>
			<ymin>21</ymin>
			<xmax>285</xmax>
			<ymax>224</ymax>
		</bndbox>
	</object>
	<object>
		<name>泡面</name>
		<pose>Left</pose>
		<truncated>0</truncated>
		<difficult>0</difficult>
		<bndbox>
			<xmin>236</xmin>
			<ymin>0</ymin>
			<xmax>372</xmax>
			<ymax>217</ymax>
		</bndbox>
	</object>
	<object>
		<name>泡面</name>
		<pose>Left</pose>
		<truncated>0</truncated>
		<difficult>0</difficult>
		<bndbox>
			<xmin>351</xmin>
			<ymin>0</ymin>
			<xmax>552</xmax>
			<ymax>190</ymax>
		</bndbox>
	</object>
	<object>
		<name>泡面</name>
		<pose>Left</pose>
		<truncated>0</truncated>
		<difficult>0</difficult>
		<bndbox>
			<xmin>531</xmin>
			<ymin>0</ymin>
			<xmax>820</xmax>
			<ymax>179</ymax>
		</bndbox>
	</object>
	<object>
		<name>泡面</name>
		<pose>Left</pose>
		<truncated>0</truncated>
		<difficult>0</difficult>
		<bndbox>
			<xmin>791</xmin>
			<ymin>0</ymin>
			<xmax>1078</xmax>
			<ymax>168</ymax>
		</bndbox>
	</object>
	<object>
		<name>泡面</name>
		<pose>Left</pose>
		<truncated>0</truncated>
		<difficult>0</difficult>
		<bndbox>
			<xmin>171</xmin>
			<ymin>212</ymin>
			<xmax>345</xmax>
			<ymax>397</ymax>
		</bndbox>
	</object>
	<object>
		<name>泡面</name>
		<pose>Left</pose>
		<truncated>0</truncated>
		<difficult>0</difficult>
		<bndbox>
			<xmin>329</xmin>
			<ymin>181</ymin>
			<xmax>540</xmax>
			<ymax>397</ymax>
		</bndbox>
	</object>
	<object>
		<name>泡面</name>
		<pose>Left</pose>
		<truncated>0</truncated>
		<difficult>0</difficult>
		<bndbox>
			<xmin>518</xmin>
			<ymin>172</ymin>
			<xmax>796</xmax>
			<ymax>413</ymax>
		</bndbox>
	</object>
	<object>
		<name>泡面</name>
		<pose>Left</pose>
		<truncated>0</truncated>
		<difficult>0</difficult>
		<bndbox>
			<xmin>780</xmin>
			<ymin>148</ymin>
			<xmax>1080</xmax>
			<ymax>410</ymax>
		</bndbox>
	</object>
	<object>
		<name>泡面</name>
		<pose>Left</pose>
		<truncated>0</truncated>
		<difficult>0</difficult>
		<bndbox>
			<xmin>138</xmin>
			<ymin>459</ymin>
			<xmax>338</xmax>
			<ymax>677</ymax>
		</bndbox>
	</object>
	<object>
		<name>泡面</name>
		<pose>Left</pose>
		<truncated>0</truncated>
		<difficult>0</difficult>
		<bndbox>
			<xmin>331</xmin>
			<ymin>459</ymin>
			<xmax>538</xmax>
			<ymax>719</ymax>
		</bndbox>
	</object>
	<object>
		<name>泡面</name>
		<pose>Left</pose>
		<truncated>0</truncated>
		<difficult>0</difficult>
		<bndbox>
			<xmin>171</xmin>
			<ymin>657</ymin>
			<xmax>347</xmax>
			<ymax>870</ymax>
		</bndbox>
	</object>
	<object>
		<name>泡面</name>
		<pose>Left</pose>
		<truncated>0</truncated>
		<difficult>0</difficult>
		<bndbox>
			<xmin>322</xmin>
			<ymin>674</ymin>
			<xmax>520</xmax>
			<ymax>906</ymax>
		</bndbox>
	</object>
	<object>
		<name>泡面</name>
		<pose>Left</pose>
		<truncated>0</truncated>
		<difficult>0</difficult>
		<bndbox>
			<xmin>543</xmin>
			<ymin>495</ymin>
			<xmax>792</xmax>
			<ymax>768</ymax>
		</bndbox>
	</object>
	<object>
		<name>泡面</name>
		<pose>Left</pose>
		<truncated>0</truncated>
		<difficult>0</difficult>
		<bndbox>
			<xmin>762</xmin>
			<ymin>519</ymin>
			<xmax>1080</xmax>
			<ymax>855</ymax>
		</bndbox>
	</object>
	<object>
		<name>泡面</name>
		<pose>Left</pose>
		<truncated>0</truncated>
		<difficult>0</difficult>
		<bndbox>
			<xmin>1009</xmin>
			<ymin>848</ymin>
			<xmax>1080</xmax>
			<ymax>1113</ymax>
		</bndbox>
	</object>
	<object>
		<name>泡面</name>
		<pose>Left</pose>
		<truncated>0</truncated>
		<difficult>0</difficult>
		<bndbox>
			<xmin>507</xmin>
			<ymin>714</ymin>
			<xmax>738</xmax>
			<ymax>993</ymax>
		</bndbox>
	</object>
	<object>
		<name>泡面</name>
		<pose>Left</pose>
		<truncated>0</truncated>
		<difficult>0</difficult>
		<bndbox>
			<xmin>716</xmin>
			<ymin>773</ymin>
			<xmax>1032</xmax>
			<ymax>1066</ymax>
		</bndbox>
	</object>
	<object>
		<name>泡面</name>
		<pose>Left</pose>
		<truncated>0</truncated>
		<difficult>0</difficult>
		<bndbox>
			<xmin>142</xmin>
			<ymin>1012</ymin>
			<xmax>325</xmax>
			<ymax>1219</ymax>
		</bndbox>
	</object>
	<object>
		<name>泡面</name>
		<pose>Left</pose>
		<truncated>0</truncated>
		<difficult>0</difficult>
		<bndbox>
			<xmin>258</xmin>
			<ymin>1097</ymin>
			<xmax>480</xmax>
			<ymax>1335</ymax>
		</bndbox>
	</object>
	<object>
		<name>泡面</name>
		<pose>Left</pose>
		<truncated>0</truncated>
		<difficult>0</difficult>
		<bndbox>
			<xmin>431</xmin>
			<ymin>1008</ymin>
			<xmax>709</xmax>
			<ymax>1293</ymax>
		</bndbox>
	</object>
	<object>
		<name>泡面</name>
		<pose>Left</pose>
		<truncated>0</truncated>
		<difficult>0</difficult>
		<bndbox>
			<xmin>458</xmin>
			<ymin>1221</ymin>
			<xmax>678</xmax>
			<ymax>1475</ymax>
		</bndbox>
	</object>
	<object>
		<name>泡面</name>
		<pose>Left</pose>
		<truncated>0</truncated>
		<difficult>0</difficult>
		<bndbox>
			<xmin>713</xmin>
			<ymin>1092</ymin>
			<xmax>1023</xmax>
			<ymax>1424</ymax>
		</bndbox>
	</object>
	<object>
		<name>泡面</name>
		<pose>Left</pose>
		<truncated>0</truncated>
		<difficult>0</difficult>
		<bndbox>
			<xmin>664</xmin>
			<ymin>1281</ymin>
			<xmax>900</xmax>
			<ymax>1619</ymax>
		</bndbox>
	</object>
	<object>
		<name>泡面</name>
		<pose>Left</pose>
		<truncated>0</truncated>
		<difficult>0</difficult>
		<bndbox>
			<xmin>894</xmin>
			<ymin>1326</ymin>
			<xmax>1080</xmax>
			<ymax>1757</ymax>
		</bndbox>
	</object>
	<object>
		<name>泡面</name>
		<pose>Left</pose>
		<truncated>0</truncated>
		<difficult>0</difficult>
		<bndbox>
			<xmin>123</xmin>
			<ymin>1262</ymin>
			<xmax>332</xmax>
			<ymax>1566</ymax>
		</bndbox>
	</object>
	<object>
		<name>泡面</name>
		<pose>Left</pose>
		<truncated>0</truncated>
		<difficult>0</difficult>
		<bndbox>
			<xmin>287</xmin>
			<ymin>1377</ymin>
			<xmax>476</xmax>
			<ymax>1684</ymax>
		</bndbox>
	</object>
	<object>
		<name>泡面</name>
		<pose>Left</pose>
		<truncated>0</truncated>
		<difficult>0</difficult>
		<bndbox>
			<xmin>476</xmin>
			<ymin>1486</ymin>
			<xmax>656</xmax>
			<ymax>1830</ymax>
		</bndbox>
	</object>
	<object>
		<name>泡面</name>
		<pose>Left</pose>
		<truncated>0</truncated>
		<difficult>0</difficult>
		<bndbox>
			<xmin>620</xmin>
			<ymin>1610</ymin>
			<xmax>916</xmax>
			<ymax>1920</ymax>
		</bndbox>
	</object>
	<object>
		<name>泡面</name>
		<pose>Left</pose>
		<truncated>0</truncated>
		<difficult>0</difficult>
		<bndbox>
			<xmin>876</xmin>
			<ymin>1781</ymin>
			<xmax>1080</xmax>
			<ymax>1920</ymax>
		</bndbox>
	</object>
	<object>
		<name>泡面</name>
		<pose>Left</pose>
		<truncated>0</truncated>
		<difficult>0</difficult>
		<bndbox>
			<xmin>140</xmin>
			<ymin>1535</ymin>
			<xmax>327</xmax>
			<ymax>1802</ymax>
		</bndbox>
	</object>
	<object>
		<name>泡面</name>
		<pose>Left</pose>
		<truncated>0</truncated>
		<difficult>0</difficult>
		<bndbox>
			<xmin>278</xmin>
			<ymin>1655</ymin>
			<xmax>485</xmax>
			<ymax>1920</ymax>
		</bndbox>
	</object>
	<object>
		<name>泡面</name>
		<pose>Left</pose>
		<truncated>0</truncated>
		<difficult>0</difficult>
		<bndbox>
			<xmin>462</xmin>
			<ymin>1806</ymin>
			<xmax>636</xmax>
			<ymax>1920</ymax>
		</bndbox>
	</object>
</annotation>