<annotation>
	<folder>goodsid</folder>
	<filename>frames_00513.jpg</filename>
	<source>
		<database>The goodsid Database</database>
		<annotation>VC goodsid</annotation>
		<image>Unknow</image>
		<flickrid>Unknow</flickrid>
	</source>
	<owner>
		<flickrid>Unknow</flickrid>
		<name>Unknow</name>
	</owner>
	<size>
		<width>1080</width>
		<height>1920</height>
		<depth>3</depth>
	</size>
	<segmented>0</segmented>
	<object>
		<name>啤酒</name>
		<pose>Left</pose>
		<truncated>0</truncated>
		<difficult>0</difficult>
		<bndbox>
			<xmin>16</xmin>
			<ymin>146</ymin>
			<xmax>116</xmax>
			<ymax>284</ymax>
		</bndbox>
	</object>
	<object>
		<name>啤酒</name>
		<pose>Left</pose>
		<truncated>0</truncated>
		<difficult>0</difficult>
		<bndbox>
			<xmin>71</xmin>
			<ymin>141</ymin>
			<xmax>165</xmax>
			<ymax>273</ymax>
		</bndbox>
	</object>
	<object>
		<name>啤酒</name>
		<pose>Left</pose>
		<truncated>0</truncated>
		<difficult>0</difficult>
		<bndbox>
			<xmin>153</xmin>
			<ymin>117</ymin>
			<xmax>238</xmax>
			<ymax>279</ymax>
		</bndbox>
	</object>
	<object>
		<name>啤酒</name>
		<pose>Left</pose>
		<truncated>0</truncated>
		<difficult>0</difficult>
		<bndbox>
			<xmin>227</xmin>
			<ymin>103</ymin>
			<xmax>325</xmax>
			<ymax>268</ymax>
		</bndbox>
	</object>
	<object>
		<name>啤酒</name>
		<pose>Left</pose>
		<truncated>0</truncated>
		<difficult>0</difficult>
		<bndbox>
			<xmin>40</xmin>
			<ymin>281</ymin>
			<xmax>112</xmax>
			<ymax>408</ymax>
		</bndbox>
	</object>
	<object>
		<name>啤酒</name>
		<pose>Left</pose>
		<truncated>0</truncated>
		<difficult>0</difficult>
		<bndbox>
			<xmin>7</xmin>
			<ymin>288</ymin>
			<xmax>63</xmax>
			<ymax>419</ymax>
		</bndbox>
	</object>
	<object>
		<name>啤酒</name>
		<pose>Left</pose>
		<truncated>0</truncated>
		<difficult>0</difficult>
		<bndbox>
			<xmin>93</xmin>
			<ymin>274</ymin>
			<xmax>165</xmax>
			<ymax>413</ymax>
		</bndbox>
	</object>
	<object>
		<name>啤酒</name>
		<pose>Left</pose>
		<truncated>0</truncated>
		<difficult>0</difficult>
		<bndbox>
			<xmin>149</xmin>
			<ymin>274</ymin>
			<xmax>229</xmax>
			<ymax>404</ymax>
		</bndbox>
	</object>
	<object>
		<name>啤酒</name>
		<pose>Left</pose>
		<truncated>0</truncated>
		<difficult>0</difficult>
		<bndbox>
			<xmin>198</xmin>
			<ymin>272</ymin>
			<xmax>263</xmax>
			<ymax>408</ymax>
		</bndbox>
	</object>
	<object>
		<name>啤酒</name>
		<pose>Left</pose>
		<truncated>0</truncated>
		<difficult>0</difficult>
		<bndbox>
			<xmin>236</xmin>
			<ymin>268</ymin>
			<xmax>314</xmax>
			<ymax>408</ymax>
		</bndbox>
	</object>
	<object>
		<name>啤酒</name>
		<pose>Left</pose>
		<truncated>0</truncated>
		<difficult>0</difficult>
		<bndbox>
			<xmin>0</xmin>
			<ymin>570</ymin>
			<xmax>56</xmax>
			<ymax>697</ymax>
		</bndbox>
	</object>
	<object>
		<name>啤酒</name>
		<pose>Left</pose>
		<truncated>0</truncated>
		<difficult>0</difficult>
		<bndbox>
			<xmin>0</xmin>
			<ymin>483</ymin>
			<xmax>74</xmax>
			<ymax>575</ymax>
		</bndbox>
	</object>
	<object>
		<name>啤酒</name>
		<pose>Left</pose>
		<truncated>0</truncated>
		<difficult>0</difficult>
		<bndbox>
			<xmin>224</xmin>
			<ymin>617</ymin>
			<xmax>298</xmax>
			<ymax>764</ymax>
		</bndbox>
	</object>
	<object>
		<name>啤酒</name>
		<pose>Left</pose>
		<truncated>0</truncated>
		<difficult>0</difficult>
		<bndbox>
			<xmin>291</xmin>
			<ymin>610</ymin>
			<xmax>376</xmax>
			<ymax>753</ymax>
		</bndbox>
	</object>
	<object>
		<name>啤酒</name>
		<pose>Left</pose>
		<truncated>0</truncated>
		<difficult>0</difficult>
		<bndbox>
			<xmin>576</xmin>
			<ymin>499</ymin>
			<xmax>656</xmax>
			<ymax>693</ymax>
		</bndbox>
	</object>
	<object>
		<name>啤酒</name>
		<pose>Left</pose>
		<truncated>0</truncated>
		<difficult>0</difficult>
		<bndbox>
			<xmin>649</xmin>
			<ymin>497</ymin>
			<xmax>745</xmax>
			<ymax>710</ymax>
		</bndbox>
	</object>
	<object>
		<name>啤酒</name>
		<pose>Left</pose>
		<truncated>0</truncated>
		<difficult>0</difficult>
		<bndbox>
			<xmin>736</xmin>
			<ymin>514</ymin>
			<xmax>845</xmax>
			<ymax>715</ymax>
		</bndbox>
	</object>
	<object>
		<name>啤酒</name>
		<pose>Left</pose>
		<truncated>0</truncated>
		<difficult>0</difficult>
		<bndbox>
			<xmin>391</xmin>
			<ymin>652</ymin>
			<xmax>472</xmax>
			<ymax>813</ymax>
		</bndbox>
	</object>
	<object>
		<name>啤酒</name>
		<pose>Left</pose>
		<truncated>0</truncated>
		<difficult>0</difficult>
		<bndbox>
			<xmin>249</xmin>
			<ymin>841</ymin>
			<xmax>314</xmax>
			<ymax>973</ymax>
		</bndbox>
	</object>
	<object>
		<name>啤酒</name>
		<pose>Left</pose>
		<truncated>0</truncated>
		<difficult>0</difficult>
		<bndbox>
			<xmin>300</xmin>
			<ymin>841</ymin>
			<xmax>367</xmax>
			<ymax>990</ymax>
		</bndbox>
	</object>
	<object>
		<name>啤酒</name>
		<pose>Left</pose>
		<truncated>0</truncated>
		<difficult>0</difficult>
		<bndbox>
			<xmin>347</xmin>
			<ymin>863</ymin>
			<xmax>407</xmax>
			<ymax>1006</ymax>
		</bndbox>
	</object>
	<object>
		<name>啤酒</name>
		<pose>Left</pose>
		<truncated>0</truncated>
		<difficult>0</difficult>
		<bndbox>
			<xmin>389</xmin>
			<ymin>863</ymin>
			<xmax>454</xmax>
			<ymax>1022</ymax>
		</bndbox>
	</object>
	<object>
		<name>啤酒</name>
		<pose>Left</pose>
		<truncated>0</truncated>
		<difficult>0</difficult>
		<bndbox>
			<xmin>240</xmin>
			<ymin>961</ymin>
			<xmax>303</xmax>
			<ymax>1079</ymax>
		</bndbox>
	</object>
	<object>
		<name>啤酒</name>
		<pose>Left</pose>
		<truncated>0</truncated>
		<difficult>0</difficult>
		<bndbox>
			<xmin>289</xmin>
			<ymin>968</ymin>
			<xmax>349</xmax>
			<ymax>1095</ymax>
		</bndbox>
	</object>
	<object>
		<name>啤酒</name>
		<pose>Left</pose>
		<truncated>0</truncated>
		<difficult>0</difficult>
		<bndbox>
			<xmin>336</xmin>
			<ymin>988</ymin>
			<xmax>398</xmax>
			<ymax>1122</ymax>
		</bndbox>
	</object>
	<object>
		<name>啤酒</name>
		<pose>Left</pose>
		<truncated>0</truncated>
		<difficult>0</difficult>
		<bndbox>
			<xmin>424</xmin>
			<ymin>1028</ymin>
			<xmax>500</xmax>
			<ymax>1168</ymax>
		</bndbox>
	</object>
	<object>
		<name>啤酒</name>
		<pose>Left</pose>
		<truncated>0</truncated>
		<difficult>0</difficult>
		<bndbox>
			<xmin>449</xmin>
			<ymin>874</ymin>
			<xmax>536</xmax>
			<ymax>1044</ymax>
		</bndbox>
	</object>
	<object>
		<name>啤酒</name>
		<pose>Left</pose>
		<truncated>0</truncated>
		<difficult>0</difficult>
		<bndbox>
			<xmin>518</xmin>
			<ymin>1279</ymin>
			<xmax>594</xmax>
			<ymax>1486</ymax>
		</bndbox>
	</object>
	<object>
		<name>啤酒</name>
		<pose>Left</pose>
		<truncated>0</truncated>
		<difficult>0</difficult>
		<bndbox>
			<xmin>578</xmin>
			<ymin>1306</ymin>
			<xmax>672</xmax>
			<ymax>1508</ymax>
		</bndbox>
	</object>
	<object>
		<name>啤酒</name>
		<pose>Left</pose>
		<truncated>0</truncated>
		<difficult>0</difficult>
		<bndbox>
			<xmin>669</xmin>
			<ymin>1368</ymin>
			<xmax>792</xmax>
			<ymax>1579</ymax>
		</bndbox>
	</object>
	<object>
		<name>啤酒</name>
		<pose>Left</pose>
		<truncated>0</truncated>
		<difficult>0</difficult>
		<bndbox>
			<xmin>767</xmin>
			<ymin>1432</ymin>
			<xmax>876</xmax>
			<ymax>1655</ymax>
		</bndbox>
	</object>
	<object>
		<name>啤酒</name>
		<pose>Left</pose>
		<truncated>0</truncated>
		<difficult>0</difficult>
		<bndbox>
			<xmin>851</xmin>
			<ymin>1472</ymin>
			<xmax>969</xmax>
			<ymax>1719</ymax>
		</bndbox>
	</object>
	<object>
		<name>啤酒</name>
		<pose>Left</pose>
		<truncated>0</truncated>
		<difficult>0</difficult>
		<bndbox>
			<xmin>613</xmin>
			<ymin>1606</ymin>
			<xmax>678</xmax>
			<ymax>1788</ymax>
		</bndbox>
	</object>
	<object>
		<name>啤酒</name>
		<pose>Left</pose>
		<truncated>0</truncated>
		<difficult>0</difficult>
		<bndbox>
			<xmin>540</xmin>
			<ymin>1572</ymin>
			<xmax>616</xmax>
			<ymax>1739</ymax>
		</bndbox>
	</object>
	<object>
		<name>啤酒</name>
		<pose>Left</pose>
		<truncated>0</truncated>
		<difficult>0</difficult>
		<bndbox>
			<xmin>351</xmin>
			<ymin>1677</ymin>
			<xmax>447</xmax>
			<ymax>1855</ymax>
		</bndbox>
	</object>
	<object>
		<name>啤酒</name>
		<pose>Left</pose>
		<truncated>0</truncated>
		<difficult>0</difficult>
		<bndbox>
			<xmin>702</xmin>
			<ymin>0</ymin>
			<xmax>788</xmax>
			<ymax>200</ymax>
		</bndbox>
	</object>
	<object>
		<name>啤酒</name>
		<pose>Left</pose>
		<truncated>0</truncated>
		<difficult>0</difficult>
		<bndbox>
			<xmin>794</xmin>
			<ymin>0</ymin>
			<xmax>902</xmax>
			<ymax>195</ymax>
		</bndbox>
	</object>
	<object>
		<name>啤酒</name>
		<pose>Left</pose>
		<truncated>0</truncated>
		<difficult>0</difficult>
		<bndbox>
			<xmin>892</xmin>
			<ymin>0</ymin>
			<xmax>1010</xmax>
			<ymax>175</ymax>
		</bndbox>
	</object>
	<object>
		<name>啤酒</name>
		<pose>Left</pose>
		<truncated>0</truncated>
		<difficult>0</difficult>
		<bndbox>
			<xmin>755</xmin>
			<ymin>199</ymin>
			<xmax>850</xmax>
			<ymax>403</ymax>
		</bndbox>
	</object>
	<object>
		<name>啤酒</name>
		<pose>Left</pose>
		<truncated>0</truncated>
		<difficult>0</difficult>
		<bndbox>
			<xmin>862</xmin>
			<ymin>180</ymin>
			<xmax>980</xmax>
			<ymax>401</ymax>
		</bndbox>
	</object>
	<object>
		<name>啤酒</name>
		<pose>Left</pose>
		<truncated>0</truncated>
		<difficult>0</difficult>
		<bndbox>
			<xmin>983</xmin>
			<ymin>178</ymin>
			<xmax>1080</xmax>
			<ymax>412</ymax>
		</bndbox>
	</object>
	<object>
		<name>啤酒</name>
		<pose>Left</pose>
		<truncated>0</truncated>
		<difficult>0</difficult>
		<bndbox>
			<xmin>911</xmin>
			<ymin>521</ymin>
			<xmax>1026</xmax>
			<ymax>744</ymax>
		</bndbox>
	</object>
	<object>
		<name>啤酒</name>
		<pose>Left</pose>
		<truncated>0</truncated>
		<difficult>0</difficult>
		<bndbox>
			<xmin>840</xmin>
			<ymin>517</ymin>
			<xmax>932</xmax>
			<ymax>725</ymax>
		</bndbox>
	</object>
	<object>
		<name>啤酒</name>
		<pose>Left</pose>
		<truncated>0</truncated>
		<difficult>0</difficult>
		<bndbox>
			<xmin>929</xmin>
			<ymin>1040</ymin>
			<xmax>1042</xmax>
			<ymax>1249</ymax>
		</bndbox>
	</object>
	<object>
		<name>啤酒</name>
		<pose>Left</pose>
		<truncated>0</truncated>
		<difficult>0</difficult>
		<bndbox>
			<xmin>919</xmin>
			<ymin>1232</ymin>
			<xmax>1021</xmax>
			<ymax>1432</ymax>
		</bndbox>
	</object>
	<object>
		<name>啤酒</name>
		<pose>Left</pose>
		<truncated>0</truncated>
		<difficult>0</difficult>
		<bndbox>
			<xmin>846</xmin>
			<ymin>1005</ymin>
			<xmax>939</xmax>
			<ymax>1205</ymax>
		</bndbox>
	</object>
	<object>
		<name>啤酒</name>
		<pose>Left</pose>
		<truncated>0</truncated>
		<difficult>0</difficult>
		<bndbox>
			<xmin>835</xmin>
			<ymin>1188</ymin>
			<xmax>921</xmax>
			<ymax>1379</ymax>
		</bndbox>
	</object>
	<object>
		<name>啤酒</name>
		<pose>Left</pose>
		<truncated>0</truncated>
		<difficult>0</difficult>
		<bndbox>
			<xmin>759</xmin>
			<ymin>989</ymin>
			<xmax>859</xmax>
			<ymax>1173</ymax>
		</bndbox>
	</object>
	<object>
		<name>啤酒</name>
		<pose>Left</pose>
		<truncated>0</truncated>
		<difficult>0</difficult>
		<bndbox>
			<xmin>746</xmin>
			<ymin>1149</ymin>
			<xmax>845</xmax>
			<ymax>1336</ymax>
		</bndbox>
	</object>
	<object>
		<name>啤酒</name>
		<pose>Left</pose>
		<truncated>0</truncated>
		<difficult>0</difficult>
		<bndbox>
			<xmin>654</xmin>
			<ymin>953</ymin>
			<xmax>740</xmax>
			<ymax>1135</ymax>
		</bndbox>
	</object>
	<object>
		<name>啤酒</name>
		<pose>Left</pose>
		<truncated>0</truncated>
		<difficult>0</difficult>
		<bndbox>
			<xmin>661</xmin>
			<ymin>1143</ymin>
			<xmax>754</xmax>
			<ymax>1304</ymax>
		</bndbox>
	</object>
	<object>
		<name>啤酒</name>
		<pose>Left</pose>
		<truncated>0</truncated>
		<difficult>0</difficult>
		<bndbox>
			<xmin>582</xmin>
			<ymin>940</ymin>
			<xmax>667</xmax>
			<ymax>1116</ymax>
		</bndbox>
	</object>
	<object>
		<name>啤酒</name>
		<pose>Left</pose>
		<truncated>0</truncated>
		<difficult>0</difficult>
		<bndbox>
			<xmin>586</xmin>
			<ymin>1117</ymin>
			<xmax>671</xmax>
			<ymax>1272</ymax>
		</bndbox>
	</object>
	<object>
		<name>啤酒</name>
		<pose>Left</pose>
		<truncated>0</truncated>
		<difficult>0</difficult>
		<bndbox>
			<xmin>1002</xmin>
			<ymin>755</ymin>
			<xmax>1080</xmax>
			<ymax>979</ymax>
		</bndbox>
	</object>
	<object>
		<name>啤酒</name>
		<pose>Left</pose>
		<truncated>0</truncated>
		<difficult>0</difficult>
		<bndbox>
			<xmin>908</xmin>
			<ymin>747</ymin>
			<xmax>1007</xmax>
			<ymax>945</ymax>
		</bndbox>
	</object>
	<object>
		<name>啤酒</name>
		<pose>Left</pose>
		<truncated>0</truncated>
		<difficult>0</difficult>
		<bndbox>
			<xmin>812</xmin>
			<ymin>724</ymin>
			<xmax>916</xmax>
			<ymax>931</ymax>
		</bndbox>
	</object>
	<object>
		<name>啤酒</name>
		<pose>Left</pose>
		<truncated>0</truncated>
		<difficult>0</difficult>
		<bndbox>
			<xmin>717</xmin>
			<ymin>720</ymin>
			<xmax>831</xmax>
			<ymax>892</ymax>
		</bndbox>
	</object>
</annotation>